aws_regions/__init__.py
aws_regions/config.py
aws_regions/endpoints.py
aws_regions-0.5.0.dist-info/licenses/LICENSE
aws_regions-0.5.0.dist-info/METADATA
aws_regions-0.5.0.dist-info/WHEEL
aws_regions-0.5.0.dist-info/top_level.txt
aws_regions-0.5.0.dist-info/RECORD
